upnpfuzz/__init__.py
upnpfuzz/_version.py
upnpfuzz/display.py
upnpfuzz/main.py
upnpfuzz/monitor.py
upnpfuzz/network.py
upnpfuzz/utils.py
upnpfuzz/fuzzers/__init__.py
upnpfuzz/fuzzers/injection.py
upnpfuzz/fuzzers/overflow.py
upnpfuzz/fuzzers/radamsa.py
upnpfuzz/generators/__init__.py
upnpfuzz/generators/base.py
upnpfuzz/generators/esp.py
upnpfuzz/generators/soap.py
upnpfuzz/generators/ssdp.py
upnpfuzz/protocols/__init__.py
upnpfuzz/protocols/base.py
upnpfuzz/protocols/esp.py
upnpfuzz/protocols/soap.py
upnpfuzz/protocols/ssdp.py
upnpfuzz-1.0.6.dist-info/LICENSE
upnpfuzz-1.0.6.dist-info/METADATA
upnpfuzz-1.0.6.dist-info/WHEEL
upnpfuzz-1.0.6.dist-info/entry_points.txt
upnpfuzz-1.0.6.dist-info/top_level.txt
upnpfuzz-1.0.6.dist-info/RECORD
