Metadata-Version: 2.2
Name: upnpfuzz
Version: 1.0.6
Summary: The Universal Plug and Play (UPnP) Fuzzer
Home-page: https://www.threat9.com
Download-URL: https://github.com/threat9/upnpfuzz/
Author: Threat9
Author-email: marcin@threat9.com
Classifier: Operating System :: POSIX
Classifier: Environment :: Console
Classifier: Environment :: Console :: Curses
Classifier: License :: OSI Approved :: BSD License
Classifier: Programming Language :: Python
Classifier: Programming Language :: Python :: 3.6
Classifier: Intended Audience :: Developers
Classifier: Intended Audience :: Education
Classifier: Intended Audience :: Information Technology
Classifier: Intended Audience :: Science/Research
Classifier: Intended Audience :: System Administrators
Classifier: Intended Audience :: Telecommunications Industry
Classifier: Topic :: Security
Classifier: Topic :: System :: Networking
Classifier: Topic :: Utilities
License-File: LICENSE
Requires-Dist: requests
Provides-Extra: dev
Requires-Dist: isort; extra == "dev"
Requires-Dist: setuptools_scm; extra == "dev"
Requires-Dist: twine; extra == "dev"
Requires-Dist: wheel; extra == "dev"
Requires-Dist: build; extra == "dev"
Requires-Dist: ruff; extra == "dev"
Dynamic: author
Dynamic: author-email
Dynamic: classifier
Dynamic: description
Dynamic: description-content-type
Dynamic: download-url
Dynamic: home-page
Dynamic: provides-extra
Dynamic: requires-dist
Dynamic: summary
